[
		{"id":1,"text":"Aguascalientes"},
		{"id":2,"text":"Baja California"},
		{"id":3,"text":"Baja California Sur"},
		{"id":4,"text":"Campeche"},
		{"id":5,"text":"Coahuila de Zaragoza"},
		{"id":6,"text":"Colima"},
		{"id":7,"text":"Chiapas"},
		{"id":8,"text":"Chihuahua"},
		{"id":9,"text":"Distrito Federal"},
		{"id":10,"text":"Durango"},
		{"id":11,"text":"Guanajuato"},
		{"id":12,"text":"Guerrero"},
		{"id":13,"text":"Hidalgo"},
		{"id":14,"text":"Jalisco"},
		{"id":15,"text":"México"},
		{"id":16,"text":"Michoacán de Ocampo"},
		{"id":17,"text":"Morelos"},
		{"id":18,"text":"Nayarit"},
		{"id":19,"text":"Nuevo León"},
		{"id":20,"text":"Oaxaca"},
		{"id":21,"text":"Puebla"},
		{"id":22,"text":"Querétaro"},
		{"id":23,"text":"Quintana Roo"},
		{"id":24,"text":"San Luis Potosí"},
		{"id":25,"text":"Sinaloa"},
		{"id":26,"text":"Sonora"},
		{"id":27,"text":"Tabasco"},
		{"id":28,"text":"Tamaulipas"},
		{"id":29,"text":"Tlaxcala"},
		{"id":30,"text":"Veracruz de Ignacio de la Llave"},
		{"id":31,"text":"Yucatán"},
		{"id":32,"text":"Zacatecas"}
	]
